<?xml version="1.0" encoding="UTF-8"?>
<java version="1.8.0_171" class="java.beans.XMLDecoder">
 <array class="java.lang.String" length="6">
  <void index="0">
   <string>foo</string>
  </void>
  <void index="1">
   <string>bla</string>
  </void>
  <void index="2">
   <string>Test - Sorting by Name</string>
  </void>
  <void index="3">
   <string>Test - Sorting by Size</string>
  </void>
  <void index="4">
   <string>Test - Error Invalid Folder</string>
  </void>
  <void index="5">
   <string>Test - creation and deletion of tags</string>
  </void>
 </array>
</java>
